eiyou.py
eiyou-0.0.2.dist-info/METADATA
eiyou-0.0.2.dist-info/WHEEL
eiyou-0.0.2.dist-info/entry_points.txt
eiyou-0.0.2.dist-info/top_level.txt
eiyou-0.0.2.dist-info/RECORD
